{
  "order": 2,
  "title": "Peekabo Glass Bottom Pool",
  "image": {
    "name": "rooftop-glass-pool",
    "file_name": "rooftop-glass-pool.jpg",
    "url": "//cdn.traveltripper.io/site-assets/192_424_22127/media/2018-12-27-044049/rooftop-glass-pool.jpg",
    "tags": "",
    "description": "",
    "date_added": "2018-12-27-044049",
    "file_type": "image/jpeg",
    "width": 732,
    "height": 411,
    "file_size": 177503,
    "url_large": "//cdn.traveltripper.io/site-assets/192_424_22127/media/2018-12-27-044049/large_rooftop-glass-pool.jpg",
    "url_medium": "//cdn.traveltripper.io/site-assets/192_424_22127/media/2018-12-27-044049/medium_rooftop-glass-pool.jpg",
    "url_small": "//cdn.traveltripper.io/site-assets/192_424_22127/media/2018-12-27-044049/small_rooftop-glass-pool.jpg",
    "url_xsmall": "//cdn.traveltripper.io/site-assets/192_424_22127/media/2018-12-27-044049/xsmall_rooftop-glass-pool.jpg",
    "url_thumb": "//cdn.traveltripper.io/site-assets/192_424_22127/media/2018-12-27-044049/thumb_rooftop-glass-pool.jpg",
    "git_file_name": "_assets/image_data/rooftop-glass-pool.json",
    "path": "//cdn.traveltripper.io/site-assets/192_424_22127/media/2018-12-27-044049/rooftop-glass-pool.jpg",
    "alt": "rooftop-glass-pool",
    "caption": ""
  },
  "description": "<p><span style=\"font-family: Arial;\"><span style=\"font-size: 16px; white-space: pre-wrap;\">Exclusive and intimate Rooftop pool with sprawling views of the beach and Ocean Drive with a magical touch &ndash; peekaboo glass bottom that is visible from the Atrium below. Reserve a balcony or terrace suite for guaranteed access and release your inner mermaid or merman.</span></span></p>\n<p><span style=\"font-family: Arial;\"><span style=\"font-size: 16px; white-space: pre-wrap;\">- 20-foot glass-bottom rooftop pool</span></span></p>\n<p><span style=\"font-family: Arial;\"><span style=\"font-size: 16px; white-space: pre-wrap;\">- Sun care products</span></span></p>\n<p>&nbsp;</p>\n<p><span style=\"font-family: Arial;\"><span style=\"font-size: 16px; white-space: pre-wrap;\">- Full Waiter Service</span></span></p>"
}